<?xml version="1.0" encoding="UTF-8"?>

<UIView layout="" attr="@:css/colors">

    <UIView layout="margin:10,marginTop:30" attr="bgColor:white,borderRadius:7,clipsToBounds:true">
    
        <FlexTextView name="" layout="height:100" attr="fontSize:14,color:black,textAlign:lef,placeholder:想说点什么..."/>


        <FlexTouchView onPress="publish" layout="" attr="underlayColor:darkGray">

            <UIImageView attr="source:Snip20181012_36" layout="width:50,height:50,margin:10"/>

        </FlexTouchView>

    </UIView>

    <UIView layout="margin:10,alignItems:flex-end" attr="">

        <FlexTouchView onPress="" layout="width:100,height:40,justifyContent:center,alignItems:center" attr="underlayColor:darkGray,bgColor:#474868,lightGray,borderRadius:7">
            <UILabel name="" layout="" attr="fontSize:14,color:white,linesNum:0,text:发布"/>
        </FlexTouchView>

    </UIView>


</UIView>
